pyencryptor/__init__.py
pyencryptor/main.py
pyencryptor3-1.0.0.dist-info/licenses/LICENSE
pyencryptor3-1.0.0.dist-info/METADATA
pyencryptor3-1.0.0.dist-info/WHEEL
pyencryptor3-1.0.0.dist-info/entry_points.txt
pyencryptor3-1.0.0.dist-info/top_level.txt
pyencryptor3-1.0.0.dist-info/RECORD
